video_filter/__init__.py
video_filter/filter.py
video_filter/stock_filters.py
video_filter-0.0.4.dist-info/LICENSE
video_filter-0.0.4.dist-info/METADATA
video_filter-0.0.4.dist-info/WHEEL
video_filter-0.0.4.dist-info/top_level.txt
video_filter-0.0.4.dist-info/RECORD
