Metadata-Version: 2.1
Name: video-filter
Version: 0.0.4
Summary: Enhance your video with filters.
Home-page: https://github.com/merijnvanes/video-filter.git
Author: Merijn van Es
Author-email: merijnvanes@gmail.com
Keywords: video,filter,color,colour,color filter,colour filter,video filter,brightness,brightness filter,video brightness,mp4,video processing,video editor tools,short,shorts,reel,reels,social,social post,social posts,social media,social media post,social media posts,cool filter,warm filter,grayscale,grayscale filter
Requires-Python: >=3.7
License-File: LICENSE
Requires-Dist: numpy
Requires-Dist: opencv-python
